django_video_embedding/__init__.py
django_video_embedding/admin.py
django_video_embedding/apps.py
django_video_embedding/fields.py
django_video_embedding/models.py
django_video_embedding/tests.py
django_video_embedding/views.py
django_video_embedding-3.5.dist-info/LICENSE
django_video_embedding-3.5.dist-info/METADATA
django_video_embedding-3.5.dist-info/WHEEL
django_video_embedding-3.5.dist-info/top_level.txt
django_video_embedding-3.5.dist-info/RECORD
